oruline
