Metadata-Version: 2.1
Name: oruline
Version: 1.0.2
Summary: Convert any Python file into a single line of code.
Home-page: https://github.com/coderganesh/1line
Author: Ganesh Kumar T K
Author-email: ganeshkumartk@outlook.com
Maintainer: Ganesh
Maintainer-email: ganeshkumartk@outlook.com
License: MIT
Keywords: obfuscate,oneliner,short,oneline,single,oruline,lambda
Platform: UNKNOWN
Classifier: Development Status :: 5 - Production/Stable
Classifier: Intended Audience :: Developers
Classifier: Topic :: Software Development :: Build Tools
Classifier: License :: OSI Approved :: MIT License
Classifier: Programming Language :: Python :: 3
Classifier: Programming Language :: Python :: 3.4
Classifier: Programming Language :: Python :: 3.5
Classifier: Programming Language :: Python :: 3.6
Classifier: Programming Language :: Python :: 3.7
